pyclassparser/__init__.py
pyclassparser-0.6.dist-info/LICENSE
pyclassparser-0.6.dist-info/METADATA
pyclassparser-0.6.dist-info/WHEEL
pyclassparser-0.6.dist-info/top_level.txt
pyclassparser-0.6.dist-info/RECORD
