Metadata-Version: 2.1
Name: pyclassparser
Version: 0.6
Summary: Parse Python classes and attributes from a string of Python code.
Author-email: "Carlos A. Planchón" <carlosandresplanchonprestes@gmail.com>
License: MIT License
Project-URL: repository, https://github.com/carlosplanchon/pyclassparser.git
Keywords: pydantic,parser,tool,schemas
Classifier: Intended Audience :: Developers
Classifier: Topic :: Software Development :: Build Tools
Classifier: License :: OSI Approved :: MIT License
Classifier: Programming Language :: Python :: 3.12
License-File: LICENSE
Requires-Dist: attrs >=23.2.0
Requires-Dist: attrs-strict >=1.0.1
